flask_pagedlist/builder.py
flask_pagedlist/__init__.py
flask_pagedlist/static/js/winf.unobtrusive-ajax.js
flask_pagedlist/static/js/winf.unobtrusive-ajax.min.js
Flask_PagedList-0.2.1.dist-info/DESCRIPTION.rst
Flask_PagedList-0.2.1.dist-info/METADATA
Flask_PagedList-0.2.1.dist-info/metadata.json
Flask_PagedList-0.2.1.dist-info/pbr.json
Flask_PagedList-0.2.1.dist-info/RECORD
Flask_PagedList-0.2.1.dist-info/top_level.txt
Flask_PagedList-0.2.1.dist-info/WHEEL
