Metadata-Version: 2.0
Name: Flask-PagedList
Version: 0.2.1
Summary: Add pypagedlist support for Flask
Home-page: https://github.com/timonwong/flask-pagedlist
Author: Timon Wong
Author-email: timon86.wang@gmail.com
License: Public Domain
Platform: UNKNOWN
Classifier: Environment :: Web Environment
Classifier: Development Status :: 4 - Beta
Classifier: Intended Audience :: Developers
Classifier: Operating System :: OS Independent
Classifier: License :: Public Domain
Classifier: Topic :: Software Development :: Libraries :: Python Modules
Classifier: Programming Language :: Python
Classifier: Programming Language :: Python :: 2
Classifier: Programming Language :: Python :: 2.6
Classifier: Programming Language :: Python :: 2.7
Classifier: Programming Language :: Python :: 3
Classifier: Programming Language :: Python :: 3.3
Requires-Dist: Flask
Requires-Dist: pypagedlist (>=0.2)
